{
    "France": [
        "61224",
        "61223",
        "1778"
    ],
    "Azerbaijan": [
        "43632",
        "39079"
    ],
    "Bangladesh": [
        "43463"
    ],
    "Belarus": [
        "41238"
    ],
    "Bolivia": [
        "39481"
    ],
    "Bulgaria": [
        "58339",
        "56183",
        "12645"
    ],
    "Denmark": [
        "56222",
        "55044",
        "27846",
        "27842",
        "25635"
    ],
    "Egypt": [
        "58497",
        "55844",
        "36830",
        "31117",
        "26470",
        "25311"
    ],
    "Italy": [
        "60573",
        "60520",
        "10294"
    ],
    "Kazakhstan": [
        "43805",
        "37749",
        "29230"
    ],
    "Lithuania": [
        "60532",
        "56987",
        "46492"
    ],
    "Australia": [
        "62006",
        "60527",
        "16275",
        "15993",
        "4321"
    ]
}